{
  "data": {
    "name": "Aitor Zaldua",
    "profession": "Blockchain Developer",
    "address": "A Corunha, Galiza.",
    "email": "aitor.zaldua@draftdigital.org",
    "website": "https://example.com",
    "phone": "xxx",
    "avatar": "xxx",
    "Profile": "This API is for the Blockchain Dev Platzi ",

    "certificate": [
      {
        "date": "Jul 2022",
        "description": "Personal Brand",
        "institution": "Platzi",
        "name": "Personal Brand"
      },
      {
        "date": "Jul 2022",
        "description": "React Professional",
        "institution": "Platzi",
        "name": "Backend Developer"
      }
    ],
    "Academic": [
      {
        "degree": "Electronic Engineer",
        "description": "Telekom Enginner, Electronic",
        "endDate": "Jun 1996",
        "institution": "UPC Barcelona",
        "startDate": "Sep 1988"
      },
      {
        "degree": "Blockchain Developer",
        "description": "Smart Contracts, Front End",
        "endDate": "Mar 2022",
        "institution": "Platzi",
        "startDate": "Jan 2022"
      },
      {
        "degree": "Smart Contract",
        "description": "Security and gas control",
        "endDate": "Mar 2022",
        "institution": "Platzi",
        "startDate": "Jan 2022"
      }
    ],
    "experience": [
      {
        "company": "Draft Digital",
        "endDate": "Present",
        "jobDescription": "Building the Web3",
        "jobTitle": "CTO",
        "startDate": "Sep 2021"
      },
      {
        "company": "DXC",
        "endDate": "Sep 2021",
        "jobDescription": "Engineer",
        "jobTitle": "BCS Engineer",
        "startDate": "Sep 2017"
      },
      {
        "company": "HP",
        "endDate": "Sep 2017",
        "jobDescription": "Engineer",
        "jobTitle": "Engineer",
        "startDate": "Sept 2000"
      }
    ],
    "skills": [
      {
        "name": "HTML5",
        "percentage": "75%"
      },
      {
        "name": "CSS",
        "percentage": "25%"
      },
      {
        "name": "JavaScript",
        "percentage": "55%"
      },
      {
        "name": "React",
        "percentage": "90%"
      }
    ],
    "interest": [
      "javascript",
      "develop",
      "backend",
      "frontend"
    ],
    "languages": [
      {
        "name": "Spanish",
        "percentage": "100%"
      },
      {
        "name": "English",
        "percentage": "90%"
      },
      {
        "name": "France",
        "percentage": "50%"
      }
    ],
    "social": [
      {
        "name": "facebook",
        "url": "https://facebook.com/"
      },
      {
        "name": "twitter",
        "url": "https://twitter.com/"
      },
      {
        "name": "github",
        "url": "https://github.com/"
      },
      {
        "name": "linkedin",
        "url": "https://www.linkedin.com/"
      }
    ]
  }
}