{
  "data": {
    "name": "Gerardo Barboni",
    "profession": "FrontEnd Developer",
    "address": "Cordoba, Argentina",
    "email": "gerardobarboni@gmail.com",
    "website": "https://gerardobarboni.com",
    "phone": "12315423156",
    "avatar": "https://avatars.githubusercontent.com/geraBarboni",
    "Profile": "Hello! I am Gera, I am 22 years old, I am from Córdoba, Argentina and I am currently looking for my first job in the IT world as a FrontEnd developer, I invite you to know a little more about me.",
    "certificate": [
      {
        "date": "Jan 2021",
        "description": "Hack up furballs try to jump onto window and fall while scratching at wall. ",
        "institution": "Platzi",
        "name": "FrontEnd Developer"
      },
      {
        "date": "Jan 2021",
        "description": "Scratch at the door then walk away wack the mini furry mouse",
        "institution": "Platzi",
        "name": "Backend Developer"
      }
    ],
    "Academic": [
      {
        "degree": "Multimedia Designer",
        "endDate": "Nov 2020",
        "institution": "IES 21",
        "startDate": "Apr 2017"
      },
      {
        "degree": "Web FrontEnd Developer",
        "endDate": "Present",
        "institution": "CoderHouse",
        "startDate": "Jan 2021"
      },
      {
        "degree": "Web3 FrontEnd Developer",
        "endDate": "Present",
        "institution": "Platzi",
        "startDate": "Jun 2022"
      }
    ],
    "experience": [
      {
        "company": "Freelance Projects",
        "endDate": "Present",
        "jobDescription": "Personal/Freelance projects to practice",
        "jobTitle": "FrontEnd Developer",
        "startDate": "May 2021"
      },
      {
        "company": "MobyDigital",
        "endDate": "May 2021",
        "jobDescription": "Create content for social media",
        "jobTitle": "Branding",
        "startDate": "Jan 2021"
      },
      {
        "company": "Barboni SRL",
        "endDate": "Dic 2019",
        "jobDescription": "Greengrocery",
        "jobTitle": "Sales",
        "startDate": "Jan 2018"
      }
    ],
    "skills": [
      {
        "name": "HTML5",
        "percentage": "75%"
      },
      {
        "name": "CSS",
        "percentage": "25%"
      },
      {
        "name": "Tailwind",
        "percentage": "25%"
      },
      {
        "name": "Sass",
        "percentage": "25%"
      },
      {
        "name": "Bootstrap",
        "percentage": "25%"
      },
      {
        "name": "JavaScript",
        "percentage": "55%"
      },
      {
        "name": "React",
        "percentage": "90%"
      },
      {
        "name": "React Native",
        "percentage": "90%"
      }
    ],
    "interest": [
      "javascript",
      "develop",
      "web3",
      "frontend"
    ],
    "languages": [
      {
        "name": "Spanish",
        "percentage": "90%"
      },
      {
        "name": "English",
        "percentage": "50%"
      },
      {
        "name": "Portuguese",
        "percentage": "50%"
      }
    ],
    "social": [
      {
        "name": "github",
        "url": "https://github.com/geraBarboni"
      },
      {
        "name": "linkedin",
        "url": "https://www.linkedin.com/in/gerardobarboni/"
      }
    ]
  }
}